{
  "collectionName": "components_podcast_highlights",
  "info": {
    "name": "item",
    "icon": "heading",
    "description": ""
  },
  "options": {},
  "attributes": {
    "image": {
      "model": "file",
      "via": "related",
      "allowedTypes": [
        "images",
        "files",
        "videos"
      ],
      "plugin": "upload",
      "required": false,
      "pluginOptions": {}
    },
    "title": {
      "type": "string"
    },
    "podcast": {
      "type": "component",
      "repeatable": true,
      "component": "podcast.podcast"
    },
    "description": {
      "type": "richtext"
    },
    "link": {
      "type": "string"
    }
  }
}
